nocodb/Base.py
nocodb/Column.py
nocodb/Record.py
nocodb/Table.py
nocodb/__init__.py
nocodb_client-0.0.1.dist-info/LICENSE
nocodb_client-0.0.1.dist-info/METADATA
nocodb_client-0.0.1.dist-info/WHEEL
nocodb_client-0.0.1.dist-info/top_level.txt
nocodb_client-0.0.1.dist-info/RECORD
