Metadata-Version: 2.1
Name: nocodb-client
Version: 0.0.1
Summary: Python client for NocoDB API v2
Author-email: liuli <525334480@qq.com>
Maintainer-email: liuli <525334480@qq.com>
License:                     GNU GENERAL PUBLIC LICENSE
Project-URL: homepage, https://github.com/liuli01/nocodb-api
Project-URL: documentation, https://github.com/liuli01/nocodb-api
Project-URL: repository, https://github.com/liuli01/nocodb-api
Project-URL: changelog, https://github.com/liuli01/nocodb-api/releases
Classifier: Development Status :: 3 - Alpha
Classifier: Programming Language :: Python
Classifier: License :: OSI Approved :: GNU General Public License v3 (GPLv3)
Requires-Python: >=3.8
License-File: LICENSE
Requires-Dist: requests
Provides-Extra: doc
Requires-Dist: pdoc; extra == "doc"
